sidekick_agent_python-0.1.2.dist-info/METADATA
sidekick_agent_python-0.1.2.dist-info/WHEEL
sidekick_agent_python-0.1.2.dist-info/RECORD
sidekick_agent_python-0.1.2.dist-info/top_level.txt
sidekick_agent_python-0.1.2.dist-info/LICENSE
tracepointdebug/cdbg_native.cpython-39-x86_64-linux-gnu.so
tracepointdebug/__init__.py
tracepointdebug/config/config_names.py
tracepointdebug/config/config_metadata.py
tracepointdebug/config/__init__.py
tracepointdebug/config/config_provider.py
tracepointdebug/trace/trace_context.py
tracepointdebug/trace/trace_support.py
tracepointdebug/trace/__init__.py
tracepointdebug/external/__init__.py
tracepointdebug/external/googleclouddebugger/rate_limit.cc
tracepointdebug/external/googleclouddebugger/bytecode_manipulator.cc
tracepointdebug/external/googleclouddebugger/version.py
tracepointdebug/external/googleclouddebugger/bytecode_breakpoint.cc
tracepointdebug/external/googleclouddebugger/module_explorer.py
tracepointdebug/external/googleclouddebugger/module_utils2.py
tracepointdebug/external/googleclouddebugger/immutability_tracer.cc
tracepointdebug/external/googleclouddebugger/imphook2.py
tracepointdebug/external/googleclouddebugger/native_module.cc
tracepointdebug/external/googleclouddebugger/module_search2.py
tracepointdebug/external/googleclouddebugger/breakpoints_manager.py
tracepointdebug/external/googleclouddebugger/python_breakpoint.py
tracepointdebug/external/googleclouddebugger/__init__.py
tracepointdebug/external/googleclouddebugger/capture_collector.py
tracepointdebug/external/googleclouddebugger/python_callback.cc
tracepointdebug/external/googleclouddebugger/leaky_bucket.cc
tracepointdebug/external/googleclouddebugger/conditional_breakpoint.cc
tracepointdebug/external/googleclouddebugger/python_util.cc
tracepointdebug/utils/__init__.py
tracepointdebug/utils/validation/__init__.py
tracepointdebug/utils/validation/validate_broker_request.py
tracepointdebug/utils/log/__init__.py
tracepointdebug/utils/log/logger.py
tracepointdebug/probe/error_stack_manager.py
tracepointdebug/probe/coded_error.py
tracepointdebug/probe/errors.py
tracepointdebug/probe/frame.py
tracepointdebug/probe/coded_exception.py
